{
    "Publico" : {
        "" : {"route":"Home"},
        "test" : {"route":"Home_Test"},
        "about" : {"route":"about"}
    },
    "wireframes" : {
        "wireframe" : {"route":"home"}
    },
    "manager" : {
        "testeb/{^[0-9]+$}/{^[a-z]+$}" : {
            "route":"common_home",
            "id": "$1",
            "idb": "$2",
            "defaults": {
                "idb": "testePadrao"
            }
        },
        "manager" : { "route":"common_home" },
        "routes" : {"route":"scope_routes"}
    }
    
}